pyharmonysearch/__init__.py
pyharmonysearch/harmony_search.py
pyharmonysearch/objective_function_interface.py
pyHarmonySearch-1.4.4.dist-info/AUTHORS.md
pyHarmonySearch-1.4.4.dist-info/LICENSE
pyHarmonySearch-1.4.4.dist-info/METADATA
pyHarmonySearch-1.4.4.dist-info/WHEEL
pyHarmonySearch-1.4.4.dist-info/top_level.txt
pyHarmonySearch-1.4.4.dist-info/RECORD
