Metadata-Version: 2.1
Name: pyHarmonySearch
Version: 1.4.4
Summary: pyHarmonySearch is a pure Python implementation of the harmony search (HS) global optimization algorithm.
Home-page: https://github.com/lanl/pyHarmonySearch
Author: Geoffrey Fairchild
Author-email: mail@gfairchild.com
Maintainer: Geoffrey Fairchild
Maintainer-email: mail@gfairchild.com
License: BSD 3-Clause License
Classifier: Development Status :: 5 - Production/Stable
Classifier: Intended Audience :: Developers
Classifier: Intended Audience :: Education
Classifier: Intended Audience :: Science/Research
Classifier: License :: OSI Approved :: BSD License
Classifier: Operating System :: OS Independent
Classifier: Programming Language :: Python :: 3
Classifier: Programming Language :: Python :: 3.7
Classifier: Programming Language :: Python :: 3.8
Classifier: Programming Language :: Python :: 3.9
Classifier: Programming Language :: Python :: 3.10
Classifier: Topic :: Scientific/Engineering :: Artificial Intelligence
License-File: LICENSE
License-File: AUTHORS.md
